pyomo_windows/__init__.py
pyomo_windows/download_solver.py
pyomo_windows/simple_model.py
pyomo_windows/solvers.py
pyomo_windows/test_solvers.py
pyomo_windows-0.0.5.dist-info/METADATA
pyomo_windows-0.0.5.dist-info/WHEEL
pyomo_windows-0.0.5.dist-info/top_level.txt
pyomo_windows-0.0.5.dist-info/RECORD
