Metadata-Version: 2.2
Name: pyomo_windows
Version: 0.0.5
Summary: Utilities to install pyomo solvers in windows without anaconda
Author-email: Oscar Neira <oneirag@yahoo.es>
Classifier: Programming Language :: Python
Classifier: License :: Other/Proprietary License
Requires-Python: >=3.11
Requires-Dist: pyomo[optional]
Requires-Dist: httpx
Requires-Dist: beautifulsoup4
Requires-Dist: ong_utils
Requires-Dist: truststore
